{
	"animations": [
		{
			"loop": false,
			"offsets": [
				0,
				0
			],
			"anim": "danceRight",
			"fps": 12,
			"name": "harry right",
			"indices": []
		},
		{
			"loop": false,
			"offsets": [
				0,
				0
			],
			"anim": "danceLeft",
			"fps": 12,
			"name": "harry left",
			"indices": []
		}
	],
	"no_antialiasing": false,
	"image": "characters/harry",
	"position": [
		0,
		0
	],
	"healthicon": "face",
	"flip_x": false,
	"healthbar_colors": [
		161,
		161,
		161
	],
	"camera_position": [
		0,
		0
	],
	"sing_duration": 6.1,
	"scale": 1.1
}